[
    {
      "question": "What's the expected wait time for my headshots?",
      "answer": "The generation time for headshots varies between 60 minutes to 2 hours, depending on server traffic. During busy times, the process might take a bit longer."
    },
    {
      "question": "How can I access my generated headshots?",
      "answer": "Once generated, your headshots will be available for preview and download under the section."
    },
    {
      "question": "What will be the resolution of my generated headshots?",
      "answer": "Our Standard and Plus plans offer high 3K+ resolution (around 3000 x 4000 pixels) ideal for professional use online or in print. \nThe Mini plan, on the other hand, provides a 768x768 resolution suitable for basic social media avatars."
    },
    {
      "question": "Is there a privacy guarantee for my photos?",
      "answer": "Absolutely, your photos remain private and can be deleted at your discretion."
    },
    {
      "question": "Am I free to use my generated headshots any way I prefer?",
      "answer": "Yes, you have full commercial rights to use the AI-generated headshots as you need."
    }
]
  